invenio_marc21/__init__.py
invenio_marc21/config.py
invenio_marc21/ext.py
invenio_marc21/version.py
invenio_marc21/views.py
invenio_marc21/mappings/__init__.py
invenio_marc21/mappings/marc21/authority/ad-v1.0.0.json
invenio_marc21/mappings/marc21/bibliographic/bd-v1.0.0.json
invenio_marc21/mappings/marc21/holdings/hd-v1.0.0.json
invenio_marc21/mappings/v5/__init__.py
invenio_marc21/mappings/v5/marc21/authority/ad-v1.0.0.json
invenio_marc21/mappings/v5/marc21/bibliographic/bd-v1.0.0.json
invenio_marc21/mappings/v5/marc21/holdings/hd-v1.0.0.json
invenio_marc21/mappings/v6/__init__.py
invenio_marc21/mappings/v6/marc21/authority/ad-v1.0.0.json
invenio_marc21/mappings/v6/marc21/bibliographic/bd-v1.0.0.json
invenio_marc21/mappings/v6/marc21/holdings/hd-v1.0.0.json
invenio_marc21/serializers/__init__.py
invenio_marc21/serializers/dojson.py
invenio_marc21/serializers/marcxml.py
invenio_marc21/templates/invenio_marc21/base.html
invenio_marc21/templates/invenio_marc21/detail.html
invenio_marc21/templates/invenio_marc21/export.html
invenio_marc21/translations/messages.pot
invenio_marc21/translations/cs/LC_MESSAGES/messages.po
invenio_marc21/translations/da/LC_MESSAGES/messages.po
invenio_marc21/translations/de/LC_MESSAGES/messages.po
invenio_marc21/translations/es/LC_MESSAGES/messages.po
invenio_marc21/translations/fr/LC_MESSAGES/messages.po
invenio_marc21/translations/it/LC_MESSAGES/messages.po
invenio_marc21/xslts/MARC21slim2MODS3-5.xsl
invenio_marc21/xslts/MARC21slim2MODS3-6.xsl
invenio_marc21/xslts/MARC21slim2OAIDC.xsl
invenio_marc21/xslts/MARC21slim2RDFDC.xsl
invenio_marc21/xslts/MARC21slim2SRWDC.xsl
invenio_marc21-1.0.0a7.dist-info/DESCRIPTION.rst
invenio_marc21-1.0.0a7.dist-info/METADATA
invenio_marc21-1.0.0a7.dist-info/RECORD
invenio_marc21-1.0.0a7.dist-info/WHEEL
invenio_marc21-1.0.0a7.dist-info/entry_points.txt
invenio_marc21-1.0.0a7.dist-info/metadata.json
invenio_marc21-1.0.0a7.dist-info/top_level.txt
