Metadata-Version: 2.0
Name: invenio-marc21
Version: 1.0.0a7
Summary: Invenio module with nice defaults for MARC21 overlay.
Home-page: https://github.com/inveniosoftware/invenio-marc21
Author: CERN
Author-email: info@inveniosoftware.org
License: MIT
Keywords: invenio MARC21
Platform: any
Classifier: Environment :: Web Environment
Classifier: Intended Audience :: Developers
Classifier: License :: OSI Approved :: MIT License
Classifier: Operating System :: OS Independent
Classifier: Programming Language :: Python
Classifier: Topic :: Internet :: WWW/HTTP :: Dynamic Content
Classifier: Topic :: Software Development :: Libraries :: Python Modules
Classifier: Programming Language :: Python :: 2
Classifier: Programming Language :: Python :: 2.7
Classifier: Programming Language :: Python :: 3
Classifier: Programming Language :: Python :: 3.5
Classifier: Programming Language :: Python :: Implementation :: CPython
Classifier: Development Status :: 1 - Planning
Provides-Extra: tests
Provides-Extra: elasticsearch2
Provides-Extra: elasticsearch5
Provides-Extra: all
Provides-Extra: docs
Provides-Extra: elasticsearch6
Requires-Dist: Flask (>=0.11.1)
Requires-Dist: Flask-BabelEx (>=0.9.3)
Requires-Dist: dojson (>=1.3.0)
Requires-Dist: invenio-jsonschemas (>=1.0.0a7)
Requires-Dist: invenio-records-rest (>=1.0.0b4)
Requires-Dist: invenio-records-ui (>=1.0.0b1)
Provides-Extra: all
Requires-Dist: Sphinx (>=1.5.2); extra == 'all'
Requires-Dist: check-manifest (>=0.25); extra == 'all'
Requires-Dist: coverage (>=4.0); extra == 'all'
Requires-Dist: invenio-db (>=1.0.0a9); extra == 'all'
Requires-Dist: invenio-i18n (>=1.0.0b4); extra == 'all'
Requires-Dist: invenio-indexer (>=1.0.0a1); extra == 'all'
Requires-Dist: invenio-pidstore (>=1.0.0a7); extra == 'all'
Requires-Dist: invenio-records (>=1.0.0a12); extra == 'all'
Requires-Dist: isort (>=4.2.2); extra == 'all'
Requires-Dist: mock (>=1.3.0); extra == 'all'
Requires-Dist: pydocstyle (>=1.0.0); extra == 'all'
Requires-Dist: pytest-cov (>=1.8.0); extra == 'all'
Requires-Dist: pytest-pep8 (>=1.0.6); extra == 'all'
Requires-Dist: pytest (>=2.8.0); extra == 'all'
Requires-Dist: Sphinx (>=1.5.2); extra == 'all'
Requires-Dist: check-manifest (>=0.25); extra == 'all'
Requires-Dist: coverage (>=4.0); extra == 'all'
Requires-Dist: invenio-db (>=1.0.0a9); extra == 'all'
Requires-Dist: invenio-i18n (>=1.0.0b4); extra == 'all'
Requires-Dist: invenio-indexer (>=1.0.0a1); extra == 'all'
Requires-Dist: invenio-pidstore (>=1.0.0a7); extra == 'all'
Requires-Dist: invenio-records (>=1.0.0a12); extra == 'all'
Requires-Dist: isort (>=4.2.2); extra == 'all'
Requires-Dist: mock (>=1.3.0); extra == 'all'
Requires-Dist: pydocstyle (>=1.0.0); extra == 'all'
Requires-Dist: pytest-cov (>=1.8.0); extra == 'all'
Requires-Dist: pytest-pep8 (>=1.0.6); extra == 'all'
Requires-Dist: pytest (>=2.8.0); extra == 'all'
Provides-Extra: docs
Requires-Dist: Sphinx (>=1.5.2); extra == 'docs'
Provides-Extra: elasticsearch2
Requires-Dist: invenio-search[elasticsearch2] (>=1.0.0b3); extra == 'elasticsearch2'
Provides-Extra: elasticsearch5
Requires-Dist: invenio-search[elasticsearch5] (>=1.0.0b3); extra == 'elasticsearch5'
Provides-Extra: elasticsearch6
Requires-Dist: invenio-search[elasticsearch6] (>=1.0.0b3); extra == 'elasticsearch6'
Provides-Extra: tests
Requires-Dist: check-manifest (>=0.25); extra == 'tests'
Requires-Dist: coverage (>=4.0); extra == 'tests'
Requires-Dist: invenio-db (>=1.0.0a9); extra == 'tests'
Requires-Dist: invenio-i18n (>=1.0.0b4); extra == 'tests'
Requires-Dist: invenio-indexer (>=1.0.0a1); extra == 'tests'
Requires-Dist: invenio-pidstore (>=1.0.0a7); extra == 'tests'
Requires-Dist: invenio-records (>=1.0.0a12); extra == 'tests'
Requires-Dist: isort (>=4.2.2); extra == 'tests'
Requires-Dist: mock (>=1.3.0); extra == 'tests'
Requires-Dist: pydocstyle (>=1.0.0); extra == 'tests'
Requires-Dist: pytest-cov (>=1.8.0); extra == 'tests'
Requires-Dist: pytest-pep8 (>=1.0.6); extra == 'tests'
Requires-Dist: pytest (>=2.8.0); extra == 'tests'
